{
  "name": "Marguerite Kelley",
  "age": 60,
  "address": {
    "street": "Ageso Park",
    "city": "Goulrac",
    "state": "NY",
    "zip": "01315"
  },
  "contact": {
    "phone": "(804) 843-9896",
    "servicePhone": "800737252"
  },
  "birthday": "1993-02-22T08:30:56.884Z",
  "ip": "210.109.160.105",
  "foo": "bar",
  "profile": {
    "about": "Nimhegzi ji ow deffazoc garmobmup fun muwwibace hupni madoros ame sok toclon sutilkob. Ifoza saraf forpac holuf coca tizugo nikanlu he hijnutva ucujo vaw cosaraku bu. Sol nah din si vakova gezi ajefi juvi weaj tacik buvcen lat tirilo za hunef dumdikbe. Zihu barwi gegnapu feviz aluhaab wu ico jaswaf nian katconev aw bahudog zecde vip. Lajifow kitav lu ja vuzulvoh pami taj fuget juwmeggur infobu puv tovwotu ukopumeh cehduv rada fanoago vaiwujen vasgivfo.",
    "bio": "Gizi onalgi poto gucwa zibperet hauphu go naip guot obag lo eri gonefo bub tukbo rewlas ib hoonofef. Tu ar minwejnos jurid mefmifib ew rihsidut betet anwoig zicichun abu getokfe. Eviivude fiwnikci unuheak isopiwzag wasomu juacace teg caga rev ruto kevbe mievvu mu beharbe puvoj ibgaiv focupe cogjep. Piwpabsom iruzoiru rop ebsak wad uhcuano mi oposepge ve variwzu ud dupfohin zembo uluijo. Oj hijsecec dojelema tasukjo be rawitkij kot li miep celmu sarlaf viwufuuju. Kedolu anaza ji cek fi ezizichab zuteru sekavzu lejzo mahof lugjo cicotet nag pozos."
  },
  "apiKey": "7b35ef79a613a3ad22037fe3564c2803bd5c892dcefa93300463232c9c76c9ca",
  "currency": {
    "code": "HUF",
    "name": "Hungary Forint"
  }
}